apt_log/__init__.py
apt_log/cli.py
apt_log/log.py
apt_log/reader.py
apt_log-0.1.dist-info/METADATA
apt_log-0.1.dist-info/WHEEL
apt_log-0.1.dist-info/entry_points.txt
apt_log-0.1.dist-info/RECORD
