Metadata-Version: 2.1
Name: apt-log
Version: 0.1
Summary: A command-line tool and module for convenient APT log file display and filtering
License: MIT
Author: Tomas Bayer
Author-email: mail@tomas.berlin
Requires-Python: >=3.11,<4.0
Classifier: License :: OSI Approved :: MIT License
Classifier: Programming Language :: Python :: 3
Classifier: Programming Language :: Python :: 3.11
Classifier: Programming Language :: Python :: 3.12
Requires-Dist: dataclass-builder (>=1.2.0,<2.0.0)
Requires-Dist: humanize (>=4.9.0,<5.0.0)
Requires-Dist: rich (>=13.7.0,<14.0.0)
Requires-Dist: typer[all] (>=0.9.0,<0.10.0)
